dbami/__init__.py
dbami/__main__.py
dbami/cli.py
dbami/constants.py
dbami/db.py
dbami/exceptions.py
dbami/pg_dump.py
dbami/py.typed
dbami/util.py
dbami/version.py
dbami/helpers/__init__.py
dbami/helpers/apply_migrations.py
dbami/helpers/helper.py
dbami-0.5.0.dist-info/licenses/LICENSE
dbami-0.5.0.dist-info/METADATA
dbami-0.5.0.dist-info/WHEEL
dbami-0.5.0.dist-info/entry_points.txt
dbami-0.5.0.dist-info/top_level.txt
dbami-0.5.0.dist-info/RECORD
